langadaptprompt/__init__.py
langadaptprompt/constants.py
langadaptprompt/paraphraser.py
langadaptprompt/promptbuilder.py
langadaptprompt/selfprompter.py
test/__init__.py
test/dialogue.py
langadaptprompt-2.22.dist-info/LICENSE
langadaptprompt-2.22.dist-info/METADATA
langadaptprompt-2.22.dist-info/WHEEL
langadaptprompt-2.22.dist-info/top_level.txt
langadaptprompt-2.22.dist-info/RECORD
